h2m2t/__init__.py
h2m2t/h2m.py
h2m2t/h2t.py
h2m2t/html.py
h2m2t/m2h.py
h2m2t/m2t.py
h2m2t/markdown.py
h2m2t/table.py
h2m2t/text.py
h2m2t-0.5.0.dist-info/licenses/LICENSE
h2m2t-0.5.0.dist-info/METADATA
h2m2t-0.5.0.dist-info/WHEEL
h2m2t-0.5.0.dist-info/top_level.txt
h2m2t-0.5.0.dist-info/RECORD
