Metadata-Version: 2.4
Name: h2m2t
Version: 0.5.0
Summary: HTML ↔ MarkDown → Text
Requires-Python: >=3.10
License-File: LICENSE
Requires-Dist: beautifulsoup4>=4.13.4
Requires-Dist: ftfy>=6.3.1
Requires-Dist: markdownify>=1.1.0
Requires-Dist: mistune>=3.1.3
Dynamic: license-file
